{
  "__AUTOGENERATED_FILE_DO_NOT_MODIFY_THIS_FILE_MANUALLY": "THERE_IS_NO_DATA_ONLY_ZUUL",
  "__INPUT_ARTIFACTS_HASH": {
    "com.fasterxml.jackson.dataformat:jackson-dataformat-yaml": 1189503110,
    "com.google.code.findbugs:jsr305": -313338248,
    "com.google.errorprone:error_prone_annotations": 227507220,
    "com.google.guava:failureaccess": -1493823684,
    "com.google.guava:guava": -2125091860,
    "com.google.j2objc:j2objc-annotations": 1772577837,
    "junit:junit": 1843337614,
    "org.checkerframework:checker-qual": -661903474,
    "org.easymock:easymock": -5618775,
    "org.hamcrest:hamcrest-core": 168210752,
    "org.ow2.asm:asm": -29138462,
    "org.slf4j:slf4j-api": 2145585153,
    "repositories": -1949687017
  },
  "__RESOLVED_ARTIFACTS_HASH": {
    "com.fasterxml.jackson.core:jackson-annotations": -799704612,
    "com.fasterxml.jackson.core:jackson-annotations:jar:sources": -1111493731,
    "com.fasterxml.jackson.core:jackson-core": -1449621545,
    "com.fasterxml.jackson.core:jackson-core:jar:sources": -1975663586,
    "com.fasterxml.jackson.core:jackson-databind": -1621382181,
    "com.fasterxml.jackson.core:jackson-databind:jar:sources": 18451414,
    "com.fasterxml.jackson.dataformat:jackson-dataformat-yaml": -505089251,
    "com.fasterxml.jackson.dataformat:jackson-dataformat-yaml:jar:sources": 355995836,
    "net.bytebuddy:byte-buddy": 2131036588,
    "net.bytebuddy:byte-buddy:jar:sources": 586932083,
    "org.easymock:easymock": 1738336513,
    "org.easymock:easymock:jar:sources": 1765148579,
    "org.objenesis:objenesis": 1536526812,
    "org.objenesis:objenesis:jar:sources": 321662415,
    "org.yaml:snakeyaml": 1733283626,
    "org.yaml:snakeyaml:jar:sources": 908659791
  },
  "artifacts": {
    "com.fasterxml.jackson.core:jackson-annotations": {
      "shasums": {
        "jar": "8aa5740d80b5a5025508b41bbadbaa1fb3772267c628b2e30681a4f45f8b8931",
        "sources": "af8d284623e54c317ec2209b3c6640f956080a46da5fb4a3001a0c9b645e53f6"
      },
      "version": "2.18.3"
    },
    "com.fasterxml.jackson.core:jackson-core": {
      "shasums": {
        "jar": "056bc4d3e5e53ce821450fa97b3f9e0f8dde125cf6da6884353bb1f09582e1d9",
        "sources": "10f173582248ac18958cc45adf9a4a6ebeecfdd54df4cda604ede609d0b6540a"
      },
      "version": "2.18.3"
    },
    "com.fasterxml.jackson.core:jackson-databind": {
      "shasums": {
        "jar": "510bdda75a7a6186c5bf33b851239488a1450906ae5757121f2e1cc48a7e108f",
        "sources": "c2906e8d0c3ff5c35658e3627f06870377e744243565198aaad00a90e5dc1d46"
      },
      "version": "2.18.3"
    },
    "com.fasterxml.jackson.dataformat:jackson-dataformat-yaml": {
      "shasums": {
        "jar": "3ca00e47cfcb43e79438ddcfc8fc735e9ebac3824fb7769138609be6bd56e483",
        "sources": "d0cc17d710f15b908940bfaf37290ddcf0f6d15c27a57c53136743687fad228b"
      },
      "version": "2.18.3"
    },
    "net.bytebuddy:byte-buddy": {
      "shasums": {
        "jar": "71568c9f8396677219f650268fbf6493ded484edcdbdf2dae6129ca5be81e8db",
        "sources": "722eaa17b935a25e994f625b32ec166c53d23770d0659c615e62a0b26ce71615"
      },
      "version": "1.17.5"
    },
    "org.easymock:easymock": {
      "shasums": {
        "jar": "63efc00da99774fb0253330ef9b5788b261022ba73f36bf76889ce7edf3d2b31",
        "sources": "42a5f5b70878719fe17f1d73486a3e11457ba949359890621d008e3472a187b6"
      },
      "version": "5.6.0"
    },
    "org.objenesis:objenesis": {
      "shasums": {
        "jar": "95488102feaf2e2858adf6b299353677dac6c15294006f8ed1c5556f8e3cd251",
        "sources": "896fa899a262c2f0f7e661848025fad22349300a5247ac175510993a9a5eede9"
      },
      "version": "3.4"
    },
    "org.yaml:snakeyaml": {
      "shasums": {
        "jar": "63a76fe66b652360bd4c2c107e6f0258daa7d4bb492008ba8c26fcd230ff9146",
        "sources": "127d0e66b80324f65821451827affb8c2f70914f0d7b7b0cb99d56d12e9901cc"
      },
      "version": "2.3"
    }
  },
  "dependencies": {
    "com.fasterxml.jackson.core:jackson-databind": [
      "com.fasterxml.jackson.core:jackson-annotations",
      "com.fasterxml.jackson.core:jackson-core"
    ],
    "com.fasterxml.jackson.dataformat:jackson-dataformat-yaml": [
      "com.fasterxml.jackson.core:jackson-core",
      "com.fasterxml.jackson.core:jackson-databind",
      "org.yaml:snakeyaml"
    ],
    "org.easymock:easymock": [
      "net.bytebuddy:byte-buddy",
      "org.objenesis:objenesis"
    ]
  },
  "packages": {
    "com.fasterxml.jackson.core:jackson-annotations": [
      "com.fasterxml.jackson.annotation"
    ],
    "com.fasterxml.jackson.core:jackson-core": [
      "com.fasterxml.jackson.core",
      "com.fasterxml.jackson.core.async",
      "com.fasterxml.jackson.core.base",
      "com.fasterxml.jackson.core.exc",
      "com.fasterxml.jackson.core.filter",
      "com.fasterxml.jackson.core.format",
      "com.fasterxml.jackson.core.internal.shaded.fdp.v2_18_3",
      "com.fasterxml.jackson.core.io",
      "com.fasterxml.jackson.core.io.schubfach",
      "com.fasterxml.jackson.core.json",
      "com.fasterxml.jackson.core.json.async",
      "com.fasterxml.jackson.core.sym",
      "com.fasterxml.jackson.core.type",
      "com.fasterxml.jackson.core.util"
    ],
    "com.fasterxml.jackson.core:jackson-databind": [
      "com.fasterxml.jackson.databind",
      "com.fasterxml.jackson.databind.annotation",
      "com.fasterxml.jackson.databind.cfg",
      "com.fasterxml.jackson.databind.deser",
      "com.fasterxml.jackson.databind.deser.impl",
      "com.fasterxml.jackson.databind.deser.std",
      "com.fasterxml.jackson.databind.exc",
      "com.fasterxml.jackson.databind.ext",
      "com.fasterxml.jackson.databind.introspect",
      "com.fasterxml.jackson.databind.jdk14",
      "com.fasterxml.jackson.databind.json",
      "com.fasterxml.jackson.databind.jsonFormatVisitors",
      "com.fasterxml.jackson.databind.jsonschema",
      "com.fasterxml.jackson.databind.jsontype",
      "com.fasterxml.jackson.databind.jsontype.impl",
      "com.fasterxml.jackson.databind.module",
      "com.fasterxml.jackson.databind.node",
      "com.fasterxml.jackson.databind.ser",
      "com.fasterxml.jackson.databind.ser.impl",
      "com.fasterxml.jackson.databind.ser.std",
      "com.fasterxml.jackson.databind.type",
      "com.fasterxml.jackson.databind.util",
      "com.fasterxml.jackson.databind.util.internal"
    ],
    "com.fasterxml.jackson.dataformat:jackson-dataformat-yaml": [
      "com.fasterxml.jackson.dataformat.yaml",
      "com.fasterxml.jackson.dataformat.yaml.snakeyaml.error",
      "com.fasterxml.jackson.dataformat.yaml.util"
    ],
    "net.bytebuddy:byte-buddy": [
      "net.bytebuddy",
      "net.bytebuddy.agent.builder",
      "net.bytebuddy.asm",
      "net.bytebuddy.build",
      "net.bytebuddy.description",
      "net.bytebuddy.description.annotation",
      "net.bytebuddy.description.enumeration",
      "net.bytebuddy.description.field",
      "net.bytebuddy.description.method",
      "net.bytebuddy.description.modifier",
      "net.bytebuddy.description.type",
      "net.bytebuddy.dynamic",
      "net.bytebuddy.dynamic.loading",
      "net.bytebuddy.dynamic.scaffold",
      "net.bytebuddy.dynamic.scaffold.inline",
      "net.bytebuddy.dynamic.scaffold.subclass",
      "net.bytebuddy.implementation",
      "net.bytebuddy.implementation.attribute",
      "net.bytebuddy.implementation.auxiliary",
      "net.bytebuddy.implementation.bind",
      "net.bytebuddy.implementation.bind.annotation",
      "net.bytebuddy.implementation.bytecode",
      "net.bytebuddy.implementation.bytecode.assign",
      "net.bytebuddy.implementation.bytecode.assign.primitive",
      "net.bytebuddy.implementation.bytecode.assign.reference",
      "net.bytebuddy.implementation.bytecode.collection",
      "net.bytebuddy.implementation.bytecode.constant",
      "net.bytebuddy.implementation.bytecode.member",
      "net.bytebuddy.jar.asm",
      "net.bytebuddy.jar.asm.commons",
      "net.bytebuddy.jar.asm.signature",
      "net.bytebuddy.jar.asmjdkbridge",
      "net.bytebuddy.matcher",
      "net.bytebuddy.pool",
      "net.bytebuddy.utility",
      "net.bytebuddy.utility.dispatcher",
      "net.bytebuddy.utility.nullability",
      "net.bytebuddy.utility.privilege",
      "net.bytebuddy.utility.visitor"
    ],
    "org.easymock:easymock": [
      "org.easymock",
      "org.easymock.internal",
      "org.easymock.internal.classinfoprovider",
      "org.easymock.internal.matchers"
    ],
    "org.objenesis:objenesis": [
      "org.objenesis",
      "org.objenesis.instantiator",
      "org.objenesis.instantiator.android",
      "org.objenesis.instantiator.annotations",
      "org.objenesis.instantiator.basic",
      "org.objenesis.instantiator.gcj",
      "org.objenesis.instantiator.perc",
      "org.objenesis.instantiator.sun",
      "org.objenesis.instantiator.util",
      "org.objenesis.strategy"
    ],
    "org.yaml:snakeyaml": [
      "org.yaml.snakeyaml",
      "org.yaml.snakeyaml.comments",
      "org.yaml.snakeyaml.composer",
      "org.yaml.snakeyaml.constructor",
      "org.yaml.snakeyaml.emitter",
      "org.yaml.snakeyaml.env",
      "org.yaml.snakeyaml.error",
      "org.yaml.snakeyaml.events",
      "org.yaml.snakeyaml.extensions.compactnotation",
      "org.yaml.snakeyaml.external.biz.base64Coder",
      "org.yaml.snakeyaml.external.com.google.gdata.util.common.base",
      "org.yaml.snakeyaml.inspector",
      "org.yaml.snakeyaml.internal",
      "org.yaml.snakeyaml.introspector",
      "org.yaml.snakeyaml.nodes",
      "org.yaml.snakeyaml.parser",
      "org.yaml.snakeyaml.reader",
      "org.yaml.snakeyaml.representer",
      "org.yaml.snakeyaml.resolver",
      "org.yaml.snakeyaml.scanner",
      "org.yaml.snakeyaml.serializer",
      "org.yaml.snakeyaml.tokens",
      "org.yaml.snakeyaml.util"
    ]
  },
  "repositories": {
    "https://repo1.maven.org/maven2/": [
      "com.fasterxml.jackson.core:jackson-annotations",
      "com.fasterxml.jackson.core:jackson-annotations:jar:sources",
      "com.fasterxml.jackson.core:jackson-core",
      "com.fasterxml.jackson.core:jackson-core:jar:sources",
      "com.fasterxml.jackson.core:jackson-databind",
      "com.fasterxml.jackson.core:jackson-databind:jar:sources",
      "com.fasterxml.jackson.dataformat:jackson-dataformat-yaml",
      "com.fasterxml.jackson.dataformat:jackson-dataformat-yaml:jar:sources",
      "net.bytebuddy:byte-buddy",
      "net.bytebuddy:byte-buddy:jar:sources",
      "org.easymock:easymock",
      "org.easymock:easymock:jar:sources",
      "org.objenesis:objenesis",
      "org.objenesis:objenesis:jar:sources",
      "org.yaml:snakeyaml",
      "org.yaml:snakeyaml:jar:sources"
    ]
  },
  "services": {
    "com.fasterxml.jackson.core:jackson-core": {
      "com.fasterxml.jackson.core.JsonFactory": [
        "com.fasterxml.jackson.core.JsonFactory"
      ]
    },
    "com.fasterxml.jackson.core:jackson-core:jar:sources": {
      "com.fasterxml.jackson.core.JsonFactory": [
        "com.fasterxml.jackson.core.JsonFactory"
      ]
    },
    "com.fasterxml.jackson.core:jackson-databind": {
      "com.fasterxml.jackson.core.ObjectCodec": [
        "com.fasterxml.jackson.databind.ObjectMapper"
      ]
    },
    "com.fasterxml.jackson.core:jackson-databind:jar:sources": {
      "com.fasterxml.jackson.core.ObjectCodec": [
        "com.fasterxml.jackson.databind.ObjectMapper"
      ]
    },
    "com.fasterxml.jackson.dataformat:jackson-dataformat-yaml": {
      "com.fasterxml.jackson.core.JsonFactory": [
        "com.fasterxml.jackson.dataformat.yaml.YAMLFactory"
      ],
      "com.fasterxml.jackson.core.ObjectCodec": [
        "com.fasterxml.jackson.dataformat.yaml.YAMLMapper"
      ]
    },
    "com.fasterxml.jackson.dataformat:jackson-dataformat-yaml:jar:sources": {
      "com.fasterxml.jackson.core.JsonFactory": [
        "com.fasterxml.jackson.dataformat.yaml.YAMLFactory"
      ],
      "com.fasterxml.jackson.core.ObjectCodec": [
        "com.fasterxml.jackson.dataformat.yaml.YAMLMapper"
      ]
    }
  },
  "version": "3"
}
